{"cameraMode":{"drawMode":0,"name":"Shaded","section":"Shading Mode"},"sceneLighting":true,"audioPlay":false,"sceneViewState":{"showFog":true,"showMaterialUpdate":false,"showSkybox":true,"showFlares":true,"showImageEffects":true,"showParticleSystems":true},"in2DMode":false,"pivot":{"x":8.412710189819336,"y":3.516040086746216,"z":5.945237159729004},"rotation":{"x":-0.04622986540198326,"y":0.1026105135679245,"z":-0.004989228211343288,"w":-0.9937118291854858},"size":4.6065592765808109,"orthographic":false}